simplis/__about__.py
simplis/__init__.py
simplis-0.0.1.dist-info/METADATA
simplis-0.0.1.dist-info/WHEEL
simplis-0.0.1.dist-info/licenses/LICENSE.txt
simplis-0.0.1.dist-info/RECORD
