Metadata-Version: 2.1
Name: simplis
Version: 0.0.1
Project-URL: Homepage, https://www.simplis.com
Author-email: "SIMPLIS Technologies, Inc." <support@simplis.com>
License-File: LICENSE.txt
Classifier: Development Status :: 1 - Planning
Classifier: Programming Language :: Python :: 3
Requires-Python: >=3.11
